yiflow/__init__.py
yiflow/bin/__init__.py
yiflow/bin/cmds.py
yiflow/bin/create.py
yiflow/core/__init__.py
yiflow/core/flow.py
yiflow/core/interface.py
yiflow/core/runner.py
yiflow/core/stage.py
yiflow/resources/example/requirements.txt
yiflow/resources/example/settings.ini
yiflow/resources/example/sourceme.sh
yiflow/resources/example/project/__init__.py
yiflow/resources/example/project/interface.py
yiflow/resources/example/project/__pycache__/__init__.cpython-310.pyc
yiflow/resources/example/project/assets/some_file.txt
yiflow/resources/example/project/configs/simple_config.py
yiflow/resources/example/project/interface/__init__.py
yiflow/resources/example/project/interface/algorithm_interface.py
yiflow/resources/example/project/interface/setting.ini
yiflow/resources/example/project/interface/__pycache__/__init__.cpython-310.pyc
yiflow/resources/example/project/interface/__pycache__/algorithm_interface.cpython-310.pyc
yiflow/resources/example/project/stages/crop_stage.py
yiflow/resources/example/project/stages/detection_stage.py
yiflow/resources/example/project/stages/rule_stage.py
yiflow/resources/example/project/stages/__pycache__/crop_stage.cpython-310.pyc
yiflow/resources/example/project/stages/__pycache__/detection_stage.cpython-310.pyc
yiflow/resources/example/project/stages/__pycache__/rule_stage.cpython-310.pyc
yiflow/resources/example/project/tests/test_interface.py
yiflow/resources/example/tests/test_image.jpg
yiflow/resources/example/tests/test_interface.py
yiflow/runners/__init__.py
yiflow/runners/onnx_runner.py
yiflow/tools/__init__.py
yiflow/tools/config_reader.py
yiflow/utils/__init__.py
yiflow/utils/deep_funcs.py
yiflow/utils/general_funcs.py
yiflow-1.2.dist-info/LICENSE
yiflow-1.2.dist-info/METADATA
yiflow-1.2.dist-info/WHEEL
yiflow-1.2.dist-info/entry_points.txt
yiflow-1.2.dist-info/top_level.txt
yiflow-1.2.dist-info/RECORD
