Metadata-Version: 2.1
Name: yiflow
Version: 1.2
Summary: Workflow library with configurable modules
Home-page: https://github.com/Redoblue/yiflow
Author: baoyuanqing
Author-email: baoyuanqing@vip.qq.com
License: MIT
Keywords: workflow
Classifier: Programming Language :: Python :: 3.6
Classifier: Programming Language :: Python :: 3.7
Classifier: Programming Language :: Python :: 3.8
Classifier: License :: OSI Approved :: MIT License
Classifier: Operating System :: OS Independent
Requires-Python: >=3.6
License-File: LICENSE
Requires-Dist: colorama (>=0.4.3)
